lwsspy.meshslice-0.0.6-py3.8-nspkg.pth
lwsspy/meshslice/__init__.py
lwsspy/meshslice/meshslice_cart.py
lwsspy/meshslice/meshslice_sph.py
lwsspy/meshslice/read_mesh.py
lwsspy/meshslice/utils/SphericalNN.py
lwsspy/meshslice/utils/__init__.py
lwsspy/meshslice/utils/cart2geo.py
lwsspy/meshslice/utils/cart2pol.py
lwsspy/meshslice/utils/cart2sph.py
lwsspy/meshslice/utils/constants.py
lwsspy/meshslice/utils/geo2cart.py
lwsspy/meshslice/utils/map_axes.py
lwsspy/meshslice/utils/plot_map.py
lwsspy/meshslice/utils/pol2cart.py
lwsspy/meshslice/utils/rotation_matrix.py
lwsspy/meshslice/utils/sph2cart.py
lwsspy/meshslice/utils/updaterc.py
lwsspy/meshslice/utils/visibility_callback.py
lwsspy/meshslice/utils/vtksphere.py
lwsspy.meshslice-0.0.6.dist-info/LICENSE
lwsspy.meshslice-0.0.6.dist-info/METADATA
lwsspy.meshslice-0.0.6.dist-info/WHEEL
lwsspy.meshslice-0.0.6.dist-info/entry_points.txt
lwsspy.meshslice-0.0.6.dist-info/namespace_packages.txt
lwsspy.meshslice-0.0.6.dist-info/top_level.txt
lwsspy.meshslice-0.0.6.dist-info/RECORD
