Metadata-Version: 2.1
Name: lwsspy.meshslice
Version: 0.0.6
Summary: Slicer for 3D Meshes.
Home-page: https://github.com/lsawade/meshslice
Author: Lucas Sawade
Author-email: lsawade@princeton.edu
Maintainer-email: lsawade@princeton.edu
License: UNKNOWN
Project-URL: Documentation, https://lsawade.github.io/meshslice
Project-URL: TravisCI, https://travis-ci.com/github/lsawade/meshslice
Keywords: Fun,Education,Learning,Programming
Platform: UNKNOWN
Classifier: Programming Language :: Python :: 3
Classifier: License :: OSI Approved :: GNU General Public License v3 or later (GPLv3+)
Classifier: Operating System :: OS Independent
Requires-Python: >=3.6
License-File: LICENSE
Requires-Dist: numpy
Requires-Dist: matplotlib
Requires-Dist: pyvista
Provides-Extra: docs
Requires-Dist: sphinx ; extra == 'docs'
Provides-Extra: tests
Requires-Dist: pytest ; extra == 'tests'
Requires-Dist: py ; extra == 'tests'
